folder2md4llms/__init__.py
folder2md4llms/__main__.py
folder2md4llms/__version__.py
folder2md4llms/cli.py
folder2md4llms/constants.py
folder2md4llms/processor.py
folder2md4llms/pyinstaller_entry.py
folder2md4llms/analyzers/__init__.py
folder2md4llms/analyzers/base_code_analyzer.py
folder2md4llms/analyzers/binary_analyzer.py
folder2md4llms/analyzers/code_analyzer.py
folder2md4llms/analyzers/config_analyzer.py
folder2md4llms/analyzers/java_analyzer.py
folder2md4llms/analyzers/javascript_analyzer.py
folder2md4llms/analyzers/priority_analyzer.py
folder2md4llms/analyzers/progressive_condenser.py
folder2md4llms/commands/__init__.py
folder2md4llms/commands/changelog.py
folder2md4llms/converters/__init__.py
folder2md4llms/converters/base.py
folder2md4llms/converters/code_converter.py
folder2md4llms/converters/converter_factory.py
folder2md4llms/converters/docx_converter.py
folder2md4llms/converters/notebook_converter.py
folder2md4llms/converters/pdf_converter.py
folder2md4llms/converters/pptx_converter.py
folder2md4llms/converters/python_converter.py
folder2md4llms/converters/rtf_converter.py
folder2md4llms/converters/smart_python_converter.py
folder2md4llms/converters/xlsx_converter.py
folder2md4llms/engine/__init__.py
folder2md4llms/engine/smart_engine.py
folder2md4llms/formatters/__init__.py
folder2md4llms/formatters/markdown.py
folder2md4llms/templates/__init__.py
folder2md4llms/templates/folder2md_ignore.template
folder2md4llms/utils/__init__.py
folder2md4llms/utils/changelog_parser.py
folder2md4llms/utils/config.py
folder2md4llms/utils/encoding.py
folder2md4llms/utils/file_strategy.py
folder2md4llms/utils/file_utils.py
folder2md4llms/utils/ignore_patterns.py
folder2md4llms/utils/ignore_suggestions.py
folder2md4llms/utils/logging_config.py
folder2md4llms/utils/platform_utils.py
folder2md4llms/utils/resource_manager.py
folder2md4llms/utils/security.py
folder2md4llms/utils/smart_budget_manager.py
folder2md4llms/utils/streaming_processor.py
folder2md4llms-0.5.15.dist-info/METADATA
folder2md4llms-0.5.15.dist-info/WHEEL
folder2md4llms-0.5.15.dist-info/entry_points.txt
folder2md4llms-0.5.15.dist-info/licenses/LICENSE
folder2md4llms-0.5.15.dist-info/RECORD
