Metadata-Version: 2.4
Name: folder2md4llms
Version: 0.5.15
Summary: A tool to convert folder structures and file contents into markdown for LLMs
Project-URL: Homepage, https://github.com/henriqueslab/folder2md4llms
Project-URL: Repository, https://github.com/henriqueslab/folder2md4llms
Project-URL: Issues, https://github.com/henriqueslab/folder2md4llms/issues
Author-email: Ricardo Henriques <ricardo@henriqueslab.org>
License: MIT
License-File: LICENSE
Classifier: Development Status :: 3 - Alpha
Classifier: Intended Audience :: Developers
Classifier: License :: OSI Approved :: MIT License
Classifier: Programming Language :: Python :: 3
Classifier: Programming Language :: Python :: 3.11
Classifier: Programming Language :: Python :: 3.12
Requires-Python: >=3.11
Requires-Dist: click>=8.0.0
Requires-Dist: henriqueslab-updater>=1.1.3
Requires-Dist: httpx>=0.24.0
Requires-Dist: markdown>=3.4.0
Requires-Dist: nbconvert>=7.0.0
Requires-Dist: openpyxl>=3.1.0
Requires-Dist: pillow>=9.0.0
Requires-Dist: psutil>=5.9.0
Requires-Dist: pygments>=2.10.0
Requires-Dist: pypdf>=4.0.0
Requires-Dist: pyperclip>=1.9.0
Requires-Dist: python-docx>=0.8.11
Requires-Dist: python-magic-bin; sys_platform == 'win32'
Requires-Dist: python-magic; sys_platform != 'win32'
Requires-Dist: python-pptx>=0.6.21
Requires-Dist: pyyaml>=6.0
Requires-Dist: rich-click>=1.6.0
Requires-Dist: rich>=13.0.0
Requires-Dist: striprtf>=0.0.26
Requires-Dist: tqdm>=4.64.0
